Workbook

Sheet ESG DDQ Appendix A
A2: Asset Characteristics | J2: Data | K2: Energy Usage | P2: Water Consumption | R2: Social | Z2: Governance
A3: Investment Vehicle | B3: Investment Name | C3: Country | D3: City | E3: Street Address | F3: Asset Class | G3: Sector / Property Type | H3: Building Status | I3: (Gross) Square Footage / Asset Size (1) | J3: Reporting Year | K3: Total Energy Consumption (kWh) | L3: % Floor Area Covered | M3: % Natural Gas and other fuels | N3: % Renewable Energy Used | O3: % Other (pls specify) | P3: Total Consumption (kGal) | Q3: Onsite water reuse (kGal) | R3: Diversity (% Women on Board) | S3: Diversity (% Women in C-suite) | T3: Work-related Accidents: Injuries | U3: Work-related Accidents: Days Lost | V3: New Hires: Total % | W3: New Hires: Turnover % | X3: Total: Turnover % | Y3: Employee Training (Type/Date) | Z3: Community Engagement (yes/no) | AA3: Community Engagement ($ spent) | AB3: Cyber Security Breaches (#) | AC3: HIPAA Violations (#) (specify if N/A)
A5: Fund 1 | B5: Parakeet | C5: United States | D5: Various | E5: Various | F5: Real Estate | G5: Manufactured Housing | H5: Standing Investment | I5: =SUM(I6:I29) -> 0 | R5: 0.4 | T5: N/A | U5: N/A | V5: 0.1463 | W5: 0 | X5: 0.242 | Y5: Fair Housing / Harassment Training
A6: APPLE | B6: Parakeet | C6: United States | D6: Deland | E6: 399 Circle Dr. | F6: Real Estate | G6: Manufactured Housing | H6: Standing Investment | J6: 1/1/2025 - 6/30/2025 | K6: =SUMIFS(Sheet1!$K:$K,Sheet1!$B:$B,'ESG DDQ Appendix A'!$A6,Sheet1!$A:$A,"Electric") -> 57015 | P6: =SUMIFS(Sheet1!$K:$K,Sheet1!$B:$B,'ESG DDQ Appendix A'!$A6,Sheet1!$A:$A,"Water")/1000 -> 0 | Z6: YES | AB6: NO | AC6: NO
A7: BELL | B7: Parakeet | C7: United States | D7: Clearwater | E7: 27554 US Hwy 19 N | F7: Real Estate | G7: Manufactured Housing | H7: Standing Investment | J7: 1/1/2025 - 6/30/2025 | K7: =SUMIFS(Sheet1!$K:$K,Sheet1!$B:$B,'ESG DDQ Appendix A'!$A7,Sheet1!$A:$A,"Electric") -> 46392 | P7: =SUMIFS(Sheet1!$K:$K,Sheet1!$B:$B,'ESG DDQ Appendix A'!$A7,Sheet1!$A:$A,"Water")/1000 -> 494 | Z7: YES | AB7: NO | AC7: NO
A8: CARL | B8: Parakeet | C8: United States | D8: Miami | E8: 4111 NW 37th Ave | F8: Real Estate | G8: Manufactured Housing | H8: Standing Investment | J8: 1/1/2025 - 6/30/2025 | K8: =SUMIFS(Sheet1!$K:$K,Sheet1!$B:$B,'ESG DDQ Appendix A'!$A8,Sheet1!$A:$A,"Electric") -> 4336 | P8: =SUMIFS(Sheet1!$K:$K,Sheet1!$B:$B,'ESG DDQ Appendix A'!$A8,Sheet1!$A:$A,"Water")/1000 -> 1478.2 | Z8: YES | AB8: NO | AC8: NO
A9: CENT | B9: Parakeet | C9: United States | D9: Cocoa | E9: 810 Peachtree Street | F9: Real Estate | G9: Manufactured Housing | H9: Standing Investment | J9: 1/1/2025 - 6/30/2025 | K9: =SUMIFS(Sheet1!$K:$K,Sheet1!$B:$B,'ESG DDQ Appendix A'!$A9,Sheet1!$A:$A,"Electric") -> 0 | P9: =SUMIFS(Sheet1!$K:$K,Sheet1!$B:$B,'ESG DDQ Appendix A'!$A9,Sheet1!$A:$A,"Water")/1000 -> 0 | Z9: YES | AB9: NO | AC9: NO
A10: CONG | B10: Parakeet | C10: United States | D10: West Palm Beach | E10: 1960 Congress Avenue | F10: Real Estate | G10: Manufactured Housing | H10: Standing Investment | J10: 1/1/2025 - 6/30/2025 | K10: =SUMIFS(Sheet1!$K:$K,Sheet1!$B:$B,'ESG DDQ Appendix A'!$A10,Sheet1!$A:$A,"Electric") -> 0 | P10: =SUMIFS(Sheet1!$K:$K,Sheet1!$B:$B,'ESG DDQ Appendix A'!$A10,Sheet1!$A:$A,"Water")/1000 -> 1225 | Z10: YES | AB10: NO | AC10: NO
A11: GEIGRV | B11: Parakeet | C11: United States | D11: Key West | E11: 5 Geiger Rd | F11: Real Estate | G11: Manufactured Housing | H11: Standing Investment | J11: 1/1/2025 - 6/30/2025 | K11: =SUMIFS(Sheet1!$K:$K,Sheet1!$B:$B,'ESG DDQ Appendix A'!$A11,Sheet1!$A:$A,"Electric") -> 0 | P11: =SUMIFS(Sheet1!$K:$K,Sheet1!$B:$B,'ESG DDQ Appendix A'!$A11,Sheet1!$A:$A,"Water")/1000 -> 0 | Z11: YES | AB11: NO | AC11: NO
A12: GKFC | B12: Parakeet | C12: United States | D12: Key West | E12: 5 Geiger Rd | F12: Real Estate | G12: Manufactured Housing | H12: Standing Investment | J12: 1/1/2025 - 6/30/2025 | K12: =SUMIFS(Sheet1!$K:$K,Sheet1!$B:$B,'ESG DDQ Appendix A'!$A12,Sheet1!$A:$A,"Electric") -> 0 | P12: =SUMIFS(Sheet1!$K:$K,Sheet1!$B:$B,'ESG DDQ Appendix A'!$A12,Sheet1!$A:$A,"Water")/1000 -> 0 | Z12: YES | AB12: NO | AC12: NO
A13: HARB | B13: Parakeet | C13: United States | D13: Cocoa | E13: 821 Peachtree Street | F13: Real Estate | G13: Manufactured Housing | H13: Standing Investment | J13: 1/1/2025 - 6/30/2025 | K13: =SUMIFS(Sheet1!$K:$K,Sheet1!$B:$B,'ESG DDQ Appendix A'!$A13,Sheet1!$A:$A,"Electric") -> 80 | P13: =SUMIFS(Sheet1!$K:$K,Sheet1!$B:$B,'ESG DDQ Appendix A'!$A13,Sheet1!$A:$A,"Water")/1000 -> 848 | Z13: YES | AB13: NO | AC13: NO
A14: HSRC | B14: Parakeet | C14: United States | D14: Crystal River | E14: 316 NE 2nd Street | F14: Real Estate | G14: Manufactured Housing | H14: Standing Investment | J14: 1/1/2025 - 6/30/2025 | K14: =SUMIFS(Sheet1!$K:$K,Sheet1!$B:$B,'ESG DDQ Appendix A'!$A14,Sheet1!$A:$A,"Electric") -> 129 | P14: =SUMIFS(Sheet1!$K:$K,Sheet1!$B:$B,'ESG DDQ Appendix A'!$A14,Sheet1!$A:$A,"Water")/1000 -> 0 | Z14: YES | AB14: NO | AC14: NO
A15: JBJ | B15: Parakeet | C15: United States | D15: Miami | E15: 2980 NW 79th St | F15: Real Estate | G15: Manufactured Housing | H15: Standing Investment | J15: 1/1/2025 - 6/30/2025 | K15: =SUMIFS(Sheet1!$K:$K,Sheet1!$B:$B,'ESG DDQ Appendix A'!$A15,Sheet1!$A:$A,"Electric") -> 29806 | P15: =SUMIFS(Sheet1!$K:$K,Sheet1!$B:$B,'ESG DDQ Appendix A'!$A15,Sheet1!$A:$A,"Water")/1000 -> 2213.332 | Z15: YES | AB15: NO | AC15: NO
A16: LS | B16: Parakeet | C16: United States | D16: Mt Dora | E16: 4301 County Road 19A | F16: Real Estate | G16: Manufactured Housing | H16: Standing Investment | J16: 1/1/2025 - 6/30/2025 | K16: =SUMIFS(Sheet1!$K:$K,Sheet1!$B:$B,'ESG DDQ Appendix A'!$A16,Sheet1!$A:$A,"Electric") -> 10434 | P16: =SUMIFS(Sheet1!$K:$K,Sheet1!$B:$B,'ESG DDQ Appendix A'!$A16,Sheet1!$A:$A,"Water")/1000 -> 530 | Z16: YES | AB16: NO | AC16: NO
A17: LUCK | B17: Parakeet | C17: United States | D17: Melbourne | E17: 635 E Eau Gallie Blvd. | F17: Real Estate | G17: Manufactured Housing | H17: Standing Investment | J17: 1/1/2025 - 6/30/2025 | K17: =SUMIFS(Sheet1!$K:$K,Sheet1!$B:$B,'ESG DDQ Appendix A'!$A17,Sheet1!$A:$A,"Electric") -> 305031 | P17: =SUMIFS(Sheet1!$K:$K,Sheet1!$B:$B,'ESG DDQ Appendix A'!$A17,Sheet1!$A:$A,"Water")/1000 -> 1149.1 | Z17: YES | AB17: NO | AC17: NO
... A29: WPMH | B29: Parakeet | C29: United States | D29: Titusville | E29: 359 Cheney Hwy | F29: Real Estate | G29: Manufactured Housing | H29: Standing Investment | J29: 1/1/2025 - 6/30/2025 | K29: =SUMIFS(Sheet1!$K:$K,Sheet1!$B:$B,'ESG DDQ Appendix A'!$A29,Sheet1!$A:$A,"Electric") -> 247968 | P29: =SUMIFS(Sheet1!$K:$K,Sheet1!$B:$B,'ESG DDQ Appendix A'!$A29,Sheet1!$A:$A,"Water")/1000 -> 158 | Z29: YES | AB29: NO | AC29: NO
A33: Fund 1 | B33: Parakeet | C33: United States | D33: Various | E33: Various | F33: Real Estate | G33: Manufactured Housing | H33: Standing Investment | I33: =SUM(I34:I57) -> 0 | R33: 0.4 | T33: N/A | U33: N/A | V33: 0.1463 | W33: 0 | X33: 0.242 | Y33: Fair Housing / Harassment Training
A34: ARD | B34: Parakeet | C34: United States | D34: Auburn | E34: 328 Carter Rd | F34: Real Estate | G34: Manufactured Housing | H34: Standing Investment
A35: BRUN | B35: Parakeet | C35: United States | D35: Brunswick | E35: 21 Gressel Circle | F35: Real Estate | G35: Manufactured Housing | H35: Standing Investment
A36: DO | B36: Parakeet | C36: United States | D36: Brunswick | E36: 4240 US Hwy 17N | F36: Real Estate | G36: Manufactured Housing | H36: Standing Investment
A37: FOX | B37: Parakeet | C37: United States | D37: Fountain Inn | E37: 491 Chapman Rd | F37: Real Estate | G37: Manufactured Housing | H37: Standing Investment
A38: GO | B38: Parakeet | C38: United States | D38: Kissimmee | E38: 4440 Yowell Road | F38: Real Estate | G38: Manufactured Housing | H38: Standing Investment
A39: GPT | B39: Parakeet | C39: United States | D39: Summerville | E39: 143 Greenpoint Dr | F39: Real Estate | G39: Manufactured Housing | H39: Standing Investment
A40: HP | B40: Parakeet | C40: United States | D40: Summerville | E40: 90 Hershey Circle | F40: Real Estate | G40: Manufactured Housing | H40: Standing Investment
A41: NGMH | B41: Parakeet | C41: United States | D41: Mims | E41: 3277 1st Ave | F41: Real Estate | G41: Manufactured Housing | H41: Standing Investment
A42: NGRV | B42: Parakeet | C42: United States | D42: Mims | E42: 3277 1st Ave | F42: Real Estate | G42: Manufactured Housing | H42: Standing Investment
A43: NGU | B43: Parakeet | C43: United States | D43: Mims | E43: 3277 1st Ave | F43: Real Estate | G43: Manufactured Housing | H43: Standing Investment
A44: OAK | B44: Parakeet | C44: United States | D44: Goose Creek | E44: 134 Oakside Dr. | F44: Real Estate | G44: Manufactured Housing | H44: Standing Investment
A45: PARK | B45: Parakeet | C45: United States | D45: West Columbia | E45: 3118 Dudley Rd | F45: Real Estate | G45: Manufactured Housing | H45: Standing Investment
... A55: WIND | B55: Parakeet | C55: United States | D55: Thonotosassa | E55: 12415 Thonotosassa Rd | F55: Real Estate | G55: Manufactured Housing | H55: Standing Investment

Sheet Bill Analysis
A1: Service Type: | B1: Site # | C1: Site Name | D1: Vendor Name | E1: Account # | F1: Service Period | G1: Days | H1: Year | I1: Month | J1: Cost | K1: Qty | L1: UOM | M1: Demand | N1: Demand UOM | O1: Rate | P1: Service Start Date | Q1: Service End Date | R1: Service Start Month | S1: Service Start Year | T1: Service End Month | U1: Service End Year
A2: Electricity | B2: AMER | C2: AMERICAN MHP | D2: NATIONAL GRID | E2: 0324600026 | F2: 06/24/2024 - 07/25/2024 | G2: 31 | H2: 2024 | I2: Jul | J2: 84.74 | K2: 141 | L2: KWH | M2: 0 | O2: Street & Security Lighting-Company Owned S-1 | P2: 45467 | Q2: 07/25/2024 | R2: 6 | S2: 2024 | T2: 7 | U2: 2024
A3: Electricity | B3: AMER | C3: AMERICAN MHP | D3: NATIONAL GRID | E3: 0324600026 | F3: 05/23/2024 - 06/24/2024 | G3: 32 | H3: 2024 | I3: Jun | J3: 87.31 | K3: 145 | L3: KWH | M3: 0 | O3: Street & Security Lighting-Company Owned S-1 | P3: 45435 | Q3: 06/24/2024 | R3: 5 | S3: 2024 | T3: 6 | U3: 2024
A4: Electricity | B4: AMER | C4: AMERICAN MHP | D4: NATIONAL GRID | E4: 0324600026 | F4: 04/24/2024 - 05/23/2024 | G4: 29 | H4: 2024 | I4: May | J4: 82.42 | K4: 143 | L4: KWH | M4: 0 | O4: Street & Security Lighting-Company Owned S-1 | P4: 45406 | Q4: 05/23/2024 | R4: 4 | S4: 2024 | T4: 5 | U4: 2024
A5: Electricity | B5: AMER | C5: AMERICAN MHP | D5: NATIONAL GRID | E5: 0324600026 | F5: 03/22/2024 - 04/24/2024 | G5: 33 | H5: 2024 | I5: Apr | J5: 101.04 | K5: 187 | L5: KWH | M5: 0 | O5: Street & Security Lighting-Company Owned S-1 | P5: 45373 | Q5: 04/24/2024 | R5: 3 | S5: 2024 | T5: 4 | U5: 2024
A6: Electricity | B6: AMER | C6: AMERICAN MHP | D6: NATIONAL GRID | E6: 0324600026 | F6: 02/22/2024 - 03/22/2024 | G6: 29 | H6: 2024 | I6: Mar | J6: 93.6 | K6: 184 | L6: KWH | M6: 0 | O6: Street & Security Lighting-Company Owned S-1 | P6: 45344 | Q6: 03/22/2024 | R6: 2 | S6: 2024 | T6: 3 | U6: 2024
A7: Electricity | B7: AMER | C7: AMERICAN MHP | D7: NATIONAL GRID | E7: 0324600026 | F7: 01/24/2024 - 02/22/2024 | G7: 29 | H7: 2024 | I7: Feb | J7: 95.42 | K7: 200 | L7: KWH | M7: 0 | O7: Street & Security Lighting-Company Owned S-1 | P7: 45315 | Q7: 02/22/2024 | R7: 1 | S7: 2024 | T7: 2 | U7: 2024
A8: Electricity | B8: AMER | C8: AMERICAN MHP | D8: NATIONAL GRID | E8: 5292896028 | F8: 06/24/2024 - 07/25/2024 | G8: 31 | H8: 2024 | I8: Jul | J8: 44.09 | K8: 62 | L8: KWH | M8: 0 | O8: Street & Security Lighting-Company Owned S-1 | P8: 45467 | Q8: 07/25/2024 | R8: 6 | S8: 2024 | T8: 7 | U8: 2024
A9: Electricity | B9: AMER | C9: AMERICAN MHP | D9: NATIONAL GRID | E9: 5292896028 | F9: 05/23/2024 - 06/24/2024 | G9: 32 | H9: 2024 | I9: Jun | J9: 45.49 | K9: 64 | L9: KWH | M9: 0 | O9: Street & Security Lighting-Company Owned S-1 | P9: 45435 | Q9: 06/24/2024 | R9: 5 | S9: 2024 | T9: 6 | U9: 2024
A10: Electricity | B10: AMER | C10: AMERICAN MHP | D10: NATIONAL GRID | E10: 5292896028 | F10: 04/24/2024 - 05/23/2024 | G10: 29 | H10: 2024 | I10: May | J10: 42.67 | K10: 63 | L10: KWH | M10: 0 | O10: Street & Security Lighting-Company Owned S-1 | P10: 45406 | Q10: 05/23/2024 | R10: 4 | S10: 2024 | T10: 5 | U10: 2024
A11: Electricity | B11: AMER | C11: AMERICAN MHP | D11: NATIONAL GRID | E11: 5292896028 | F11: 03/22/2024 - 04/24/2024 | G11: 33 | H11: 2024 | I11: Apr | J11: 51.96 | K11: 83 | L11: KWH | M11: 0 | O11: Street & Security Lighting-Company Owned S-1 | P11: 45373 | Q11: 04/24/2024 | R11: 3 | S11: 2024 | T11: 4 | U11: 2024
A12: Electricity | B12: AMER | C12: AMERICAN MHP | D12: NATIONAL GRID | E12: 5292896028 | F12: 02/22/2024 - 03/22/2024 | G12: 29 | H12: 2024 | I12: Mar | J12: 47.56 | K12: 81 | L12: KWH | M12: 0 | O12: Street & Security Lighting-Company Owned S-1 | P12: 45344 | Q12: 03/22/2024 | R12: 2 | S12: 2024 | T12: 3 | U12: 2024
A13: Electricity | B13: AMER | C13: AMERICAN MHP | D13: NATIONAL GRID | E13: 5292896028 | F13: 01/24/2024 - 02/22/2024 | G13: 29 | H13: 2024 | I13: Feb | J13: 48.63 | K13: 89 | L13: KWH | M13: 0 | O13: Street & Security Lighting-Company Owned S-1 | P13: 45315 | Q13: 02/22/2024 | R13: 1 | S13: 2024 | T13: 2 | U13: 2024
A14: Water | B14: AMER | C14: AMERICAN MHP | D14: AUBURN WATER DISTRICT | E14: 29220 | F14: 03/21/2024 - 06/20/2024 | G14: 91 | H14: 2024 | I14: Jul | J14: 17081.93 | K14: 1144470 | L14: GAL | O14: None | P14: 45372 | Q14: 45463 | R14: 3 | S14: 2024 | T14: 6 | U14: 2024
A15: Electricity | B15: APPLE | C15: APPLEGATE MHC | D15: DUKE ENERGY PAYMENT PROCESSING | E15: 910087354836 | F15: 06/12/2024 - 07/11/2024 | G15: 29 | H15: 2024 | I15: Jul | J15: 747.87 | K15: 5786 | L15: KWH | M15: 14.82 | N15: KW | O15: GENERAL SERVICE DEMAND SEC (GSD-1) | P15: 45455 | Q15: 07/11/2024 | R15: 6 | S15: 2024 | T15: 7 | U15: 2024
A16: Electricity | B16: APPLE | C16: APPLEGATE MHC | D16: DUKE ENERGY PAYMENT PROCESSING | E16: 910087354836 | F16: 05/11/2024 - 06/11/2024 | G16: 31 | H16: 2024 | I16: Jun | J16: 776.26 | K16: 5853 | L16: KWH | M16: 13.74 | N16: KW | O16: GENERAL SERVICE DEMAND SEC (GSD-1) | P16: 45423 | Q16: 06/11/2024 | R16: 5 | S16: 2024 | T16: 6 | U16: 2024
A17: Electricity | B17: APPLE | C17: APPLEGATE MHC | D17: DUKE ENERGY PAYMENT PROCESSING | E17: 910087354836 | F17: 04/11/2024 - 05/10/2024 | G17: 29 | H17: 2024 | I17: May | J17: 716.64 | K17: 4791 | L17: KWH | M17: 14.55 | N17: KW | O17: GENERAL SERVICE DEMAND SEC (GSD-1) | P17: 45393 | Q17: 05/10/2024 | R17: 4 | S17: 2024 | T17: 5 | U17: 2024
A18: Electricity | B18: APPLE | C18: APPLEGATE MHC | D18: DUKE ENERGY PAYMENT PROCESSING | E18: 910087354836 | F18: 03/13/2024 - 04/10/2024 | G18: 28 | H18: 2024 | I18: Apr | J18: 614.31 | K18: 4108 | L18: KWH | M18: 12.26 | N18: KW | O18: GENERAL SERVICE DEMAND SEC (GSD-1) | P18: 45364 | Q18: 04/10/2024 | R18: 3 | S18: 2024 | T18: 4 | U18: 2024
A19: Electricity | B19: APPLE | C19: APPLEGATE MHC | D19: DUKE ENERGY PAYMENT PROCESSING | E19: 910087354836 | F19: 02/13/2024 - 03/12/2024 | G19: 28 | H19: 2024 | I19: Mar | J19: 679.47 | K19: 4462 | L19: KWH | M19: 13.39 | N19: KW | O19: GENERAL SERVICE DEMAND SEC (GSD-1) | P19: 45335 | Q19: 03/12/2024 | R19: 2 | S19: 2024 | T19: 3 | U19: 2024
A20: Electricity | B20: APPLE | C20: APPLEGATE MHC | D20: DUKE ENERGY PAYMENT PROCESSING | E20: 910087354836 | F20: 01/12/2024 - 02/12/2024 | G20: 31 | H20: 2024 | I20: Feb | J20: 868.85 | K20: 5888 | L20: KWH | M20: 17.35 | N20: KW | O20: GENERAL SERVICE DEMAND SEC (GSD-1) | P20: 45303 | Q20: 02/12/2024 | R20: 1 | S20: 2024 | T20: 2 | U20: 2024
A21: Electricity | B21: APPLE | C21: APPLEGATE MHC | D21: DUKE ENERGY PAYMENT PROCESSING | E21: 910087354836 | F21: 01/11/2024 - 02/13/2024 | G21: 33 | H21: 2024 | I21: Feb | J21: 877.35 | K21: 0 | L21: KWH | M21: 0 | O21: GENERAL SERVICE DEMAND SEC (GSD-1) | P21: 45302 | Q21: 02/13/2024 | R21: 1 | S21: 2024 | T21: 2 | U21: 2024
A22: Electricity | B22: APPLE | C22: APPLEGATE MHC | D22: DUKE ENERGY PAYMENT PROCESSING | E22: 910087354836 | F22: 01/11/2024 - 02/13/2024 | G22: 33 | H22: 2024 | I22: Feb | J22: 877.35 | K22: 0 | L22: KWH | M22: 0 | O22: GENERAL SERVICE DEMAND SEC (GSD-1) | P22: 45302 | Q22: 02/13/2024 | R22: 1 | S22: 2024 | T22: 2 | U22: 2024
A23: Electricity | B23: APPLE | C23: APPLEGATE MHC | D23: DUKE ENERGY PAYMENT PROCESSING | E23: 910087354977 | F23: 06/11/2024 - 07/10/2024 | G23: 29 | H23: 2024 | I23: Jul | J23: 157.75 | K23: 487 | L23: KWH | M23: 0 | O23: LIGHTING SERVICE COMPANY OWNED/MAINTAINED (LS-1) | P23: 45454 | Q23: 07/10/2024 | R23: 6 | S23: 2024 | T23: 7 | U23: 2024
A24: Electricity | B24: APPLE | C24: APPLEGATE MHC | D24: DUKE ENERGY PAYMENT PROCESSING | E24: 910087354977 | F24: 05/10/2024 - 06/10/2024 | G24: 31 | H24: 2024 | I24: Jun | J24: 164.65 | K24: 487 | L24: KWH | M24: 0 | O24: LIGHTING SERVICE COMPANY OWNED/MAINTAINED (LS-1) | P24: 45422 | Q24: 06/10/2024 | R24: 5 | S24: 2024 | T24: 6 | U24: 2024
A25: Electricity | B25: APPLE | C25: APPLEGATE MHC | D25: DUKE ENERGY PAYMENT PROCESSING | E25: 910087354977 | F25: 04/10/2024 - 05/09/2024 | G25: 29 | H25: 2024 | I25: May | J25: 167.56 | K25: 487 | L25: KWH | M25: 0 | O25: LIGHTING SERVICE COMPANY OWNED/MAINTAINED (LS-1) | P25: 45392 | Q25: 05/09/2024 | R25: 4 | S25: 2024 | T25: 5 | U25: 2024
A26: Electricity | B26: APPLE | C26: APPLEGATE MHC | D26: DUKE ENERGY PAYMENT PROCESSING | E26: 910087354977 | F26: 03/12/2024 - 04/09/2024 | G26: 28 | H26: 2024 | I26: Apr | J26: 167.56 | K26: 487 | L26: KWH | M26: 0 | O26: LIGHTING SERVICE COMPANY OWNED/MAINTAINED (LS-1) | P26: 45363 | Q26: 04/09/2024 | R26: 3 | S26: 2024 | T26: 4 | U26: 2024
A27: Electricity | B27: APPLE | C27: APPLEGATE MHC | D27: DUKE ENERGY PAYMENT PROCESSING | E27: 910087354977 | F27: 02/10/2024 - 03/11/2024 | G27: 30 | H27: 2024 | I27: Mar | J27: 167.53 | K27: 487 | L27: KWH | M27: 0 | O27: LIGHTING SERVICE COMPANY OWNED/MAINTAINED (LS-1) | P27: 45332 | Q27: 03/11/2024 | R27: 2 | S27: 2024 | T27: 3 | U27: 2024
A28: Electricity | B28: CARL | C28: CARLEY S MOBILE HOME PARK | D28: FPL | E28: 6338187369 | F28: 05/14/2024 - 06/13/2024 | G28: 30 | H28: 2024 | I28: Jun | J28: 208.74 | K28: 574 | L28: KWH | M28: 0 | O28: SL-1 STREET LIGHTING SERVICE | P28: 45426 | Q28: 06/13/2024 | R28: 5 | S28: 2024 | T28: 6 | U28: 2024
A29: Electricity | B29: CARL | C29: CARLEY S MOBILE HOME PARK | D29: FPL | E29: 6338187369 | F29: 04/12/2024 - 07/15/2024 | G29: 94 | H29: 2024 | I29: Jul | J29: 192.72 | K29: 840 | L29: KWH | M29: 0 | O29: SL-1 STREET LIGHTING SERVICE | P29: 45394 | Q29: 07/15/2024 | R29: 4 | S29: 2024 | T29: 7 | U29: 2024
A30: Electricity | B30: CARL | C30: CARLEY S MOBILE HOME PARK | D30: FPL | E30: 6338187369 | F30: 04/12/2024 - 05/14/2024 | G30: 32 | H30: 2024 | I30: May | J30: 219.78 | K30: 574 | L30: KWH | M30: 0 | O30: SL-1 STREET LIGHTING SERVICE | P30: 45394 | Q30: 05/14/2024 | R30: 4 | S30: 2024 | T30: 5 | U30: 2024
A31: Electricity | B31: CARL | C31: CARLEY S MOBILE HOME PARK | D31: FPL | E31: 6338187369 | F31: 03/13/2024 - 04/12/2024 | G31: 30 | H31: 2024 | I31: Apr | J31: 224.7 | K31: 574 | L31: KWH | M31: 0 | O31: SL-1 STREET LIGHTING SERVICE | P31: 45364 | Q31: 04/12/2024 | R31: 3 | S31: 2024 | T31: 4 | U31: 2024
A32: Electricity | B32: CARL | C32: CARLEY S MOBILE HOME PARK | D32: FPL | E32: 6338187369 | F32: 02/13/2024 - 03/13/2024 | G32: 29 | H32: 2024 | I32: Mar | J32: 233.47 | K32: 574 | L32: KWH | M32: 0 | O32: SL-1 STREET LIGHTING SERVICE | P32: 45335 | Q32: 03/13/2024 | R32: 2 | S32: 2024 | T32: 3 | U32: 2024
... A45: Electricity | B45: CARL | C45: CARLEY S MOBILE HOME PARK | D45: FPL | E45: 9657990025 | F45: 01/24/2024 - 02/23/2024 | G45: 30 | H45: 2024 | I45: Feb | J45: 114.35 | K45: 763 | L45: KWH | M45: 0 | O45: RS-1 RESIDENTIAL SERVICE | P45: 45315 | Q45: 02/23/2024 | R45: 1 | S45: 2024 | T45: 2 | U45: 2024
A46: Sewer | B46: CARL | C46: CARLEY S MOBILE HOME PARK | D46: CITY OF HIALEAH | E46: 235032000 | F46: 01/26/2024 - 03/26/2024 | G46: 60 | H46: 2024 | I46: Apr | J46: 202.57 | K46: 3528 | L46: GAL | P46: 45317 | Q46: 03/26/2024 | R46: 1 | S46: 2024 | T46: 3 | U46: 2024
A47: Water | B47: CARL | C47: CARLEY S MOBILE HOME PARK | D47: CITY OF HIALEAH | E47: 235032000 | F47: 03/26/2024 - 05/28/2024 | G47: 63 | H47: 2024 | I47: Jun | J47: 2478.91 | K47: 375700 | L47: GAL | P47: 45377 | Q47: 05/28/2024 | R47: 3 | S47: 2024 | T47: 5 | U47: 2024
A48: Water | B48: CARL | C48: CARLEY S MOBILE HOME PARK | D48: CITY OF HIALEAH | E48: 235032000 | F48: 01/26/2024 - 03/26/2024 | G48: 60 | H48: 2024 | I48: Apr | J48: 2146.69 | K48: 3528 | L48: GAL | P48: 45317 | Q48: 03/26/2024 | R48: 1 | S48: 2024 | T48: 3 | U48: 2024
A49: Water | B49: CARL | C49: CARLEY S MOBILE HOME PARK | D49: CITY OF HIALEAH | E49: 235033000 | F49: 03/26/2024 - 05/28/2024 | G49: 63 | H49: 2024 | I49: Jun | J49: 18897.77 | K49: 999800 | L49: GAL | P49: 45377 | Q49: 05/28/2024 | R49: 3 | S49: 2024 | T49: 5 | U49: 2024
A50: Water | B50: CARL | C50: CARLEY S MOBILE HOME PARK | D50: CITY OF HIALEAH | E50: 235033000 | F50: 01/26/2024 - 03/26/2024 | G50: 60 | H50: 2024 | I50: Apr | J50: 5746.14 | K50: 867900 | L50: GAL | P50: 45317 | Q50: 03/26/2024 | R50: 1 | S50: 2024 | T50: 3 | U50: 2024
A51: Electricity | B51: CENTHARB | C51: CENTRAL MOBILE HOME PARK | D51: FPL | E51: 4251646057 | F51: 05/07/2024 - 06/06/2024 | G51: 30 | H51: 2024 | I51: Jun | J51: 41.69 | K51: 105 | L51: KWH | M51: 0 | O51: GS-1 GENERAL SVC NON-DEMAND / BUSINESS | P51: 45419 | Q51: 06/06/2024 | R51: 5 | S51: 2024 | T51: 6 | U51: 2024
A52: Electricity | B52: CENTHARB | C52: CENTRAL MOBILE HOME PARK | D52: FPL | E52: 4251646057 | F52: 04/05/2024 - 05/07/2024 | G52: 32 | H52: 2024 | I52: May | J52: 37.63 | K52: 115 | L52: KWH | M52: 0 | O52: GS-1 GENERAL SVC NON-DEMAND/BUSINESS | P52: 45387 | Q52: 05/07/2024 | R52: 4 | S52: 2024 | T52: 5 | U52: 2024
A53: Electricity | B53: CENTHARB | C53: CENTRAL MOBILE HOME PARK | D53: FPL | E53: 4251646057 | F53: 03/06/2024 - 04/05/2024 | G53: 30 | H53: 2024 | I53: Apr | J53: 38.3 | K53: 109 | L53: KWH | M53: 0 | O53: GS-1 GENERAL SVC NON-DEMAND / BUSINESS | P53: 45357 | Q53: 04/05/2024 | R53: 3 | S53: 2024 | T53: 4 | U53: 2024
A54: Electricity | B54: CENTHARB | C54: CENTRAL MOBILE HOME PARK | D54: FPL | E54: 4251646057 | F54: 02/06/2024 - 03/06/2024 | G54: 29 | H54: 2024 | I54: Mar | J54: 46.16 | K54: 140 | L54: KWH | M54: 0 | O54: GS-1 GENERAL SVC NON-DEMAND / BUSINESS | P54: 45328 | Q54: 03/06/2024 | R54: 2 | S54: 2024 | T54: 3 | U54: 2024
A55: Electricity | B55: CENTHARB | C55: CENTRAL MOBILE HOME PARK | D55: FPL | E55: 4408902270 | F55: 06/06/2024 - 07/08/2024 | G55: 32 | H55: 2024 | I55: Jul | J55: 34.31 | K55: 103 | L55: KWH | M55: 0 | O55: RS-1 RESIDENTIAL SERVICE | P55: 45449 | Q55: 07/08/2024 | R55: 6 | S55: 2024 | T55: 7 | U55: 2024
A56: Electricity | B56: CENTHARB | C56: CENTRAL MOBILE HOME PARK | D56: FPL | E56: 4408902270 | F56: 05/07/2024 - 06/06/2024 | G56: 30 | H56: 2024 | I56: Jun | J56: 34.95 | K56: 118 | L56: KWH | M56: 0 | O56: RS-1 RESIDENTIAL SERVICE | P56: 45419 | Q56: 06/06/2024 | R56: 5 | S56: 2024 | T56: 6 | U56: 2024
A57: Electricity | B57: CENTHARB | C57: CENTRAL MOBILE HOME PARK | D57: FPL | E57: 4408902270 | F57: 04/05/2024 - 05/07/2024 | G57: 32 | H57: 2024 | I57: May | J57: 36.19 | K57: 147 | L57: KWH | M57: 0 | O57: RS-1 RESIDENTIAL SERVICE | P57: 45387 | Q57: 05/07/2024 | R57: 4 | S57: 2024 | T57: 5 | U57: 2024
A58: Electricity | B58: CENTHARB | C58: CENTRAL MOBILE HOME PARK | D58: FPL | E58: 4408902270 | F58: 03/06/2024 - 04/05/2024 | G58: 30 | H58: 2024 | I58: Apr | J58: 36.87 | K58: 137 | L58: KWH | M58: 0 | O58: RS-1 RESIDENTIAL SERVICE | P58: 45357 | Q58: 04/05/2024 | R58: 3 | S58: 2024 | T58: 4 | U58: 2024
A59: Electricity | B59: CENTHARB | C59: CENTRAL MOBILE HOME PARK | D59: FPL | E59: 4408902270 | F59: 03/06/2024 - 04/05/2024 | G59: 30 | H59: 2024 | I59: Apr | J59: 36.87 | K59: 137 | L59: KWH | M59: 0 | O59: RS-1 RESIDENTIAL SERVICE | P59: 45357 | Q59: 04/05/2024 | R59: 3 | S59: 2024 | T59: 4 | U59: 2024
A60: Electricity | B60: CENTHARB | C60: CENTRAL MOBILE HOME PARK | D60: FPL | E60: 4408902270 | F60: 03/06/2024 - 04/05/2024 | G60: 30 | H60: 2024 | I60: Apr | J60: 36.87 | K60: 137 | L60: KWH | M60: 0 | O60: RS-1 RESIDENTIAL SERVICE | P60: 45357 | Q60: 04/05/2024 | R60: 3 | S60: 2024 | T60: 4 | U60: 2024
A61: Electricity | B61: CENTHARB | C61: CENTRAL MOBILE HOME PARK | D61: FPL | E61: 4408902270 | F61: 03/06/2024 - 04/05/2024 | G61: 30 | H61: 2024 | I61: Apr | J61: 36.87 | K61: 137 | L61: KWH | M61: 0 | O61: RS-1 RESIDENTIAL SERVICE | P61: 45357 | Q61: 04/05/2024 | R61: 3 | S61: 2024 | T61: 4 | U61: 2024
A62: Electricity | B62: CENTHARB | C62: CENTRAL MOBILE HOME PARK | D62: FPL | E62: 4408902270 | F62: 02/06/2024 - 03/06/2024 | G62: 29 | H62: 2024 | I62: Mar | J62: 40.96 | K62: 188 | L62: KWH | M62: 0 | O62: RS-1 RESIDENTIAL SERVICE | P62: 45328 | Q62: 03/06/2024 | R62: 2 | S62: 2024 | T62: 3 | U62: 2024
A63: Electricity | B63: CENTHARB | C63: CENTRAL MOBILE HOME PARK | D63: FPL | E63: 4408902270 | F63: 01/05/2024 - 02/06/2024 | G63: 32 | H63: 2024 | I63: Feb | J63: 38.25 | K63: 142 | L63: KWH | M63: 0 | O63: RS-1 RESIDENTIAL SERVICE | P63: 45296 | Q63: 02/06/2024 | R63: 1 | S63: 2024 | T63: 2 | U63: 2024
A64: Gas | B64: CENTHARB | C64: CENTRAL MOBILE HOME PARK | D64: FLORIDA CITY GAS | E64: 1181923 | F64: 06/26/2024 - 07/25/2024 | G64: 29 | H64: 2024 | I64: Jul | J64: 62.5 | K64: 14 | L64: THMS | O64: 820-814: GS-1 Sales | P64: 45469 | Q64: 45498 | R64: 6 | S64: 2024 | T64: 7 | U64: 2024
A65: Gas | B65: CENTHARB | C65: CENTRAL MOBILE HOME PARK | D65: FLORIDA CITY GAS | E65: 1181923 | F65: 05/24/2024 - 06/26/2024 | G65: 33 | H65: 2024 | I65: Jul | J65: 68.96 | K65: 18 | L65: THMS | O65: 820-814: GS-1 Sales | P65: 45436 | Q65: 45469 | R65: 5 | S65: 2024 | T65: 6 | U65: 2024
A66: Gas | B66: CENTHARB | C66: CENTRAL MOBILE HOME PARK | D66: FLORIDA CITY GAS | E66: 1181923 | F66: 04/25/2024 - 05/24/2024 | G66: 29 | H66: 2024 | I66: May | J66: 64.58 | K66: 15 | L66: THMS | O66: 820-814: GS-1 Sales | P66: 45407 | Q66: 45436 | R66: 4 | S66: 2024 | T66: 5 | U66: 2024
A67: Gas | B67: CENTHARB | C67: CENTRAL MOBILE HOME PARK | D67: FLORIDA CITY GAS | E67: 1181923 | F67: 03/27/2024 - 04/25/2024 | G67: 29 | H67: 2024 | I67: May | J67: 71.02 | K67: 19 | L67: THMS | O67: 820-814: GS-1 Sales | P67: 45378 | Q67: 45407 | R67: 3 | S67: 2024 | T67: 4 | U67: 2024
A68: Gas | B68: CENTHARB | C68: CENTRAL MOBILE HOME PARK | D68: FLORIDA CITY GAS | E68: 1181923 | F68: 02/27/2024 - 03/27/2024 | G68: 29 | H68: 2024 | I68: Apr | J68: 76.31 | K68: 22 | L68: THMS | O68: 820-814: GS-1 Sales | P68: 45349 | Q68: 45378 | R68: 2 | S68: 2024 | T68: 3 | U68: 2024
A69: Gas | B69: CENTHARB | C69: CENTRAL MOBILE HOME PARK | D69: FLORIDA CITY GAS | E69: 1181923 | F69: 01/29/2024 - 02/27/2024 | G69: 29 | H69: 2024 | I69: Mar | J69: 86.74 | K69: 29 | L69: THMS | O69: 820-814: GS-1 Sales | P69: 45320 | Q69: 45349 | R69: 1 | S69: 2024 | T69: 2 | U69: 2024
A70: Sewer | B70: CENTHARB | C70: CENTRAL MOBILE HOME PARK | D70: CITY OF COCOA | E70: 48972111978 | F70: 06/17/2024 - 07/17/2024 | G70: 30 | H70: 2024 | I70: Jul | J70: 2563.05 | K70: 289000 | L70: GAL | P70: 45460 | Q70: 07/17/2024 | R70: 6 | S70: 2024 | T70: 7 | U70: 2024
A71: Sewer | B71: CENTHARB | C71: CENTRAL MOBILE HOME PARK | D71: CITY OF COCOA | E71: 48972111978 | F71: 05/16/2024 - 06/17/2024 | G71: 32 | H71: 2024 | I71: Jun | J71: 2906.08 | K71: 312000 | L71: GAL | P71: 45428 | Q71: 06/17/2024 | R71: 5 | S71: 2024 | T71: 6 | U71: 2024
A72: Sewer | B72: CENTHARB | C72: CENTRAL MOBILE HOME PARK | D72: CITY OF COCOA | E72: 48972111978 | F72: 04/15/2024 - 05/16/2024 | G72: 31 | H72: 2024 | I72: May | J72: 2348.9 | K72: 258000 | L72: GAL | P72: 45397 | Q72: 05/16/2024 | R72: 4 | S72: 2024 | T72: 5 | U72: 2024
A73: Sewer | B73: CENTHARB | C73: CENTRAL MOBILE HOME PARK | D73: CITY OF COCOA | E73: 48972111978 | F73: 03/14/2024 - 04/15/2024 | G73: 32 | H73: 2024 | I73: Apr | J73: 2149.28 | K73: 248000 | L73: GAL | P73: 45365 | Q73: 04/15/2024 | R73: 3 | S73: 2024 | T73: 4 | U73: 2024
A74: Sewer | B74: CENTHARB | C74: CENTRAL MOBILE HOME PARK | D74: CITY OF COCOA | E74: 48972111978 | F74: 02/15/2024 - 03/14/2024 | G74: 28 | H74: 2024 | I74: Mar | J74: 2072.35 | K74: 228000 | L74: GAL | P74: 45337 | Q74: 03/14/2024 | R74: 2 | S74: 2024 | T74: 3 | U74: 2024
A75: Sewer | B75: CENTHARB | C75: CENTRAL MOBILE HOME PARK | D75: CITY OF COCOA | E75: 48972111978 | F75: 02/15/2024 - 03/14/2024 | G75: 28 | H75: 2024 | I75: Mar | J75: 1296.41 | K75: 228000 | L75: GAL | P75: 45337 | Q75: 03/14/2024 | R75: 2 | S75: 2024 | T75: 3 | U75: 2024
A76: Sewer | B76: CENTHARB | C76: CENTRAL MOBILE HOME PARK | D76: CITY OF COCOA | E76: 48972111978 | F76: 01/17/2024 - 02/15/2024 | G76: 29 | H76: 2024 | I76: Feb | J76: 2233.43 | K76: 223000 | L76: GAL | P76: 45308 | Q76: 02/15/2024 | R76: 1 | S76: 2024 | T76: 2 | U76: 2024
A77: Water | B77: CENTHARB | C77: CENTRAL MOBILE HOME PARK | D77: CITY OF COCOA | E77: 48972111978 | F77: 06/17/2024 - 07/17/2024 | G77: 30 | H77: 2024 | I77: Jul | J77: 3647.67 | K77: 289000 | L77: GAL | P77: 45460 | Q77: 07/17/2024 | R77: 6 | S77: 2024 | T77: 7 | U77: 2024
A78: Water | B78: CENTHARB | C78: CENTRAL MOBILE HOME PARK | D78: CITY OF COCOA | E78: 48972111978 | F78: 05/16/2024 - 06/17/2024 | G78: 32 | H78: 2024 | I78: Jun | J78: 4235.83 | K78: 312000 | L78: GAL | P78: 45428 | Q78: 06/17/2024 | R78: 5 | S78: 2024 | T78: 6 | U78: 2024
A79: Water | B79: CENTHARB | C79: CENTRAL MOBILE HOME PARK | D79: CITY OF COCOA | E79: 48972111978 | F79: 04/15/2024 - 05/16/2024 | G79: 31 | H79: 2024 | I79: May | J79: 3212.18 | K79: 258000 | L79: GAL | P79: 45397 | Q79: 05/16/2024 | R79: 4 | S79: 2024 | T79: 5 | U79: 2024
A80: Water | B80: CENTHARB | C80: CENTRAL MOBILE HOME PARK | D80: CITY OF COCOA | E80: 48972111978 | F80: 03/14/2024 - 04/15/2024 | G80: 32 | H80: 2024 | I80: Apr | J80: 2894.57 | K80: 248000 | L80: GAL | P80: 45365 | Q80: 04/15/2024 | R80: 3 | S80: 2024 | T80: 4 | U80: 2024
A81: Water | B81: CENTHARB | C81: CENTRAL MOBILE HOME PARK | D81: CITY OF COCOA | E81: 48972111978 | F81: 02/15/2024 - 03/14/2024 | G81: 28 | H81: 2024 | I81: Mar | J81: 2449.84 | K81: 228000 | L81: GAL | P81: 45337 | Q81: 03/14/2024 | R81: 2 | S81: 2024 | T81: 3 | U81: 2024
... A83: Water | B83: CENTHARB | C83: CENTRAL MOBILE HOME PARK | D83: CITY OF COCOA | E83: 48972111978 | F83: 01/17/2024 - 02/15/2024 | G83: 29 | H83: 2024 | I83: Feb | J83: 2874.82 | K83: 223000 | L83: GAL | P83: 45308 | Q83: 02/15/2024 | R83: 1 | S83: 2024 | T83: 2 | U83: 2024
A84: Electricity | B84: CONG | C84: CONGRESS MOBILE HOME PARK | D84: FPL | E84: 8767133419 | F84: 01/09/2024 - 01/29/2024 | G84: 20 | H84: 2024 | I84: Apr | J84: -47.83 | K84: 58 | L84: KWH | M84: 0 | O84: OL-1 OUTDOOR LIGHTING | P84: 45300 | Q84: 01/29/2024 | R84: 1 | S84: 2024 | T84: 1 | U84: 2024
A85: Sewer | B85: CONG | C85: CONGRESS MOBILE HOME PARK | D85: PALM BEACH COUNTY WTR UTIL DPT | E85: 1000901242 | F85: 06/28/2024 - 07/25/2024 | G85: 27 | H85: 2024 | I85: Aug | J85: 1005.13 | K85: 203000 | L85: GAL | P85: 45471 | Q85: 07/25/2024 | R85: 6 | S85: 2024 | T85: 7 | U85: 2024
A86: Sewer | B86: CONG | C86: CONGRESS MOBILE HOME PARK | D86: PALM BEACH COUNTY WTR UTIL DPT | E86: 1000901242 | F86: 05/23/2024 - 06/28/2024 | G86: 36 | H86: 2024 | I86: Jul | J86: 1083.82 | K86: 246000 | L86: GAL | P86: 45435 | Q86: 06/28/2024 | R86: 5 | S86: 2024 | T86: 6 | U86: 2024
A87: Sewer | B87: CONG | C87: CONGRESS MOBILE HOME PARK | D87: PALM BEACH COUNTY WTR UTIL DPT | E87: 1000901242 | F87: 04/23/2024 - 05/23/2024 | G87: 30 | H87: 2024 | I87: Jun | J87: 1032.58 | K87: 218000 | L87: GAL | P87: 45405 | Q87: 05/23/2024 | R87: 4 | S87: 2024 | T87: 5 | U87: 2024
A88: Sewer | B88: CONG | C88: CONGRESS MOBILE HOME PARK | D88: PALM BEACH COUNTY WTR UTIL DPT | E88: 1000901242 | F88: 03/25/2024 - 04/23/2024 | G88: 29 | H88: 2024 | I88: May | J88: 1003.3 | K88: 202000 | L88: GAL | P88: 45376 | Q88: 04/23/2024 | R88: 3 | S88: 2024 | T88: 4 | U88: 2024
A89: Sewer | B89: CONG | C89: CONGRESS MOBILE HOME PARK | D89: PALM BEACH COUNTY WTR UTIL DPT | E89: 1000901242 | F89: 02/29/2024 - 03/25/2024 | G89: 25 | H89: 2024 | I89: Apr | J89: 946.57 | K89: 171000 | L89: GAL | P89: 45351 | Q89: 03/25/2024 | R89: 2 | S89: 2024 | T89: 3 | U89: 2024
A90: Sewer | B90: CONG | C90: CONGRESS MOBILE HOME PARK | D90: PALM BEACH COUNTY WTR UTIL DPT | E90: 1000901242 | F90: 01/31/2024 - 02/29/2024 | G90: 29 | H90: 2024 | I90: Mar | J90: 993.35 | K90: 192000 | L90: GAL | P90: 45322 | Q90: 02/29/2024 | R90: 1 | S90: 2024 | T90: 2 | U90: 2024
A91: Sewer | B91: CONG | C91: CONGRESS MOBILE HOME PARK | D91: PALM BEACH COUNTY WTR UTIL DPT | E91: 1000901242 | F91: 01/02/2024 - 01/31/2024 | G91: 29 | H91: 2024 | I91: Feb | J91: 1079.62 | K91: 234000 | L91: GAL | P91: 45293 | Q91: 01/31/2024 | R91: 1 | S91: 2024 | T91: 1 | U91: 2024
A92: Water | B92: CONG | C92: CONGRESS MOBILE HOME PARK | D92: PALM BEACH COUNTY WTR UTIL DPT | E92: 1000901242 | F92: 06/28/2024 - 07/25/2024 | G92: 27 | H92: 2024 | I92: Aug | J92: 904.81 | K92: 203000 | L92: GAL | O92: R | P92: 45471 | Q92: 07/25/2024 | R92: 6 | S92: 2024 | T92: 7 | U92: 2024
A93: Water | B93: CONG | C93: CONGRESS MOBILE HOME PARK | D93: PALM BEACH COUNTY WTR UTIL DPT | E93: 1000901242 | F93: 05/23/2024 - 06/28/2024 | G93: 36 | H93: 2024 | I93: Jul | J93: 1080.25 | K93: 246000 | L93: GAL | O93: R | P93: 45435 | Q93: 06/28/2024 | R93: 5 | S93: 2024 | T93: 6 | U93: 2024
A94: Water | B94: CONG | C94: CONGRESS MOBILE HOME PARK | D94: PALM BEACH COUNTY WTR UTIL DPT | E94: 1000901242 | F94: 04/23/2024 - 05/23/2024 | G94: 30 | H94: 2024 | I94: Jun | J94: 966.01 | K94: 218000 | L94: GAL | O94: R | P94: 45405 | Q94: 05/23/2024 | R94: 4 | S94: 2024 | T94: 5 | U94: 2024
A95: Water | B95: CONG | C95: CONGRESS MOBILE HOME PARK | D95: PALM BEACH COUNTY WTR UTIL DPT | E95: 1000901242 | F95: 03/25/2024 - 04/23/2024 | G95: 29 | H95: 2024 | I95: May | J95: 900.73 | K95: 202000 | L95: GAL | O95: R | P95: 45376 | Q95: 04/23/2024 | R95: 3 | S95: 2024 | T95: 4 | U95: 2024
A96: Water | B96: CONG | C96: CONGRESS MOBILE HOME PARK | D96: PALM BEACH COUNTY WTR UTIL DPT | E96: 1000901242 | F96: 02/29/2024 - 03/25/2024 | G96: 25 | H96: 2024 | I96: Apr | J96: 774.25 | K96: 171000 | L96: GAL | O96: R | P96: 45351 | Q96: 03/25/2024 | R96: 2 | S96: 2024 | T96: 3 | U96: 2024
A97: Water | B97: CONG | C97: CONGRESS MOBILE HOME PARK | D97: PALM BEACH COUNTY WTR UTIL DPT | E97: 1000901242 | F97: 01/31/2024 - 02/29/2024 | G97: 29 | H97: 2024 | I97: Mar | J97: 867.22 | K97: 192000 | L97: GAL | O97: R | P97: 45322 | Q97: 02/29/2024 | R97: 1 | S97: 2024 | T97: 2 | U97: 2024
A98: Water | B98: CONG | C98: CONGRESS MOBILE HOME PARK | D98: PALM BEACH COUNTY WTR UTIL DPT | E98: 1000901242 | F98: 01/02/2024 - 01/31/2024 | G98: 29 | H98: 2024 | I98: Feb | J98: 1048.53 | K98: 234000 | L98: GAL | O98: R | P98: 45293 | Q98: 01/31/2024 | R98: 1 | S98: 2024 | T98: 1 | U98: 2024
A99: Electricity | B99: GKRV | C99: GEIGER KEY RESORT | D99: KEYS ENERGY SERVICES | E99: 768012612 | F99: 06/17/2024 - 07/17/2024 | G99: 30 | H99: 2024 | I99: Jul | J99: 7775.46 | K99: 52040 | L99: KWH | M99: 113.6 | N99: KW | O99: COM 214 | P99: 45460 | Q99: 07/17/2024 | R99: 6 | S99: 2024 | T99: 7 | U99: 2024
A100: Electricity | B100: GKRV | C100: GEIGER KEY RESORT | D100: KEYS ENERGY SERVICES | E100: 768012612 | F100: 05/17/2024 - 06/17/2024 | G100: 31 | H100: 2024 | I100: Jun | J100: 7546.97 | K100: 50120 | L100: KWH | M100: 93.6 | N100: KW | O100: COM 214 | P100: 45429 | Q100: 06/17/2024 | R100: 5 | S100: 2024 | T100: 6 | U100: 2024
A101: Electricity | B101: GKRV | C101: GEIGER KEY RESORT | D101: KEYS ENERGY SERVICES | E101: 768012612 | F101: 04/17/2024 - 05/17/2024 | G101: 30 | H101: 2024 | I101: May | J101: 6799.9 | K101: 44000 | L101: KWH | M101: 86 | N101: KW | O101: COM 214 | P101: 45399 | Q101: 05/17/2024 | R101: 4 | S101: 2024 | T101: 5 | U101: 2024
A102: Electricity | B102: GKRV | C102: GEIGER KEY RESORT | D102: KEYS ENERGY SERVICES | E102: 768012612 | F102: 03/18/2024 - 04/17/2024 | G102: 30 | H102: 2024 | I102: Apr | J102: 6517.13 | K102: 40960 | L102: KWH | M102: 118 | N102: KW | O102: COM 214 | P102: 45369 | Q102: 04/17/2024 | R102: 3 | S102: 2024 | T102: 4 | U102: 2024
A103: Electricity | B103: GKRV | C103: GEIGER KEY RESORT | D103: KEYS ENERGY SERVICES | E103: 768012612 | F103: 02/22/2024 - 02/22/2024 | G103: 0 | H103: 2024 | I103: Feb | J103: 11186.18 | K103: 0 | L103: KWH | M103: 0 | O103: COM 214 | P103: 45344 | Q103: 02/22/2024 | R103: 2 | S103: 2024 | T103: 2 | U103: 2024
A104: Electricity | B104: GKRV | C104: GEIGER KEY RESORT | D104: KEYS ENERGY SERVICES | E104: 768012612 | F104: 02/16/2024 - 03/18/2024 | G104: 31 | H104: 2024 | I104: Mar | J104: 6726.01 | K104: 43360 | L104: KWH | M104: 92.4 | N104: KW | O104: COM 214 | P104: 45338 | Q104: 03/18/2024 | R104: 2 | S104: 2024 | T104: 3 | U104: 2024
A105: Electricity | B105: GKRV | C105: GEIGER KEY RESORT | D105: KEYS ENERGY SERVICES | E105: 768012612 | F105: 01/17/2024 - 02/16/2024 | G105: 30 | H105: 2024 | I105: Feb | J105: 5401.48 | K105: 33800 | L105: KWH | M105: 98.8 | N105: KW | O105: COM 214 | P105: 45308 | Q105: 02/16/2024 | R105: 1 | S105: 2024 | T105: 2 | U105: 2024
A106: Electricity | B106: GKRV | C106: GEIGER KEY RESORT | D106: KEYS ENERGY SERVICES | E106: 768012701 | F106: 06/17/2024 - 07/17/2024 | G106: 30 | H106: 2024 | I106: Jul | J106: 1413.19 | K106: 9463 | L106: KWH | M106: 19.83 | N106: KW | O106: COM SM 210 | P106: 45460 | Q106: 07/17/2024 | R106: 6 | S106: 2024 | T106: 7 | U106: 2024
A107: Electricity | B107: GKRV | C107: GEIGER KEY RESORT | D107: KEYS ENERGY SERVICES | E107: 768012701 | F107: 05/17/2024 - 06/17/2024 | G107: 31 | H107: 2024 | I107: Jun | J107: 1435.34 | K107: 9616 | L107: KWH | M107: 20.71 | N107: KW | O107: COM SM 210 | P107: 45429 | Q107: 06/17/2024 | R107: 5 | S107: 2024 | T107: 6 | U107: 2024
A108: Electricity | B108: GKRV | C108: GEIGER KEY RESORT | D108: KEYS ENERGY SERVICES | E108: 768012701 | F108: 04/17/2024 - 05/17/2024 | G108: 30 | H108: 2024 | I108: May | J108: 1156.73 | K108: 7303 | L108: KWH | M108: 18.51 | N108: KW | O108: COM SM 210 | P108: 45399 | Q108: 05/17/2024 | R108: 4 | S108: 2024 | T108: 5 | U108: 2024
A109: Electricity | B109: GKRV | C109: GEIGER KEY RESORT | D109: KEYS ENERGY SERVICES | E109: 768012701 | F109: 03/18/2024 - 04/17/2024 | G109: 30 | H109: 2024 | I109: Apr | J109: 1131.99 | K109: 7523 | L109: KWH | M109: 22.29 | N109: KW | O109: COM SM 210 | P109: 45369 | Q109: 04/17/2024 | R109: 3 | S109: 2024 | T109: 4 | U109: 2024
A110: Electricity | B110: GKRV | C110: GEIGER KEY RESORT | D110: KEYS ENERGY SERVICES | E110: 768012701 | F110: 02/16/2024 - 03/18/2024 | G110: 31 | H110: 2024 | I110: Mar | J110: 1186.92 | K110: 7695 | L110: KWH | M110: 21.26 | N110: KW | O110: COM SM 210 | P110: 45338 | Q110: 03/18/2024 | R110: 2 | S110: 2024 | T110: 3 | U110: 2024
A111: Gas | B111: GKRV | C111: GEIGER KEY RESORT | D111: AMERIGAS | E111: 204019977 | F111: 03/14/2024 - 03/20/2024 | G111: 6 | H111: 2024 | I111: Mar | J111: 323.03 | K111: 0 | L111: THMS | O111: None | P111: 45365 | Q111: 45371 | R111: 3 | S111: 2024 | T111: 3 | U111: 2024
A112: Gas | B112: GKRV | C112: GEIGER KEY RESORT | D112: AMERIGAS | E112: 204019977 | F112: 03/09/2024 - 03/14/2024 | G112: 5 | H112: 2024 | I112: Mar | J112: 235.06 | K112: 0 | L112: THMS | P112: 45360 | Q112: 45365 | R112: 3 | S112: 2024 | T112: 3 | U112: 2024
A113: Gas | B113: GKRV | C113: GEIGER KEY RESORT | D113: AMERIGAS | E113: 204019977 | F113: 02/29/2024 - 02/29/2024 | G113: 0 | H113: 2024 | I113: Feb | J113: 190.57 | K113: 77 | L113: THMS | O113: None | P113: 45351 | Q113: 45351 | R113: 2 | S113: 2024 | T113: 2 | U113: 2024
...

Sheet Sheet1
A1: Service Type: | B1: Site # | C1: Site Name | D1: Vendor Name | E1: Account # | F1: Service Period | G1: Days | H1: Year | I1: Month | J1: Cost | K1: Qty | L1: UOM | M1: Demand | N1: Demand UOM | O1: Rate | P1: Service Start Date | Q1: Service End Date | R1: Service Start Month | S1: Service Start Year | T1: Service End Month | U1: Service End Year
A2: Electric | B2: CA | C2: CRYSTAL ACRES | D2: WITHLACOOCHEE RIVER ELEC COOP | E2: 122850NCREDE | F2: 12/13/2024 - 01/16/2025 | G2: 34 | H2: 2025 | I2: Jan | J2: 64.67 | K2: 169 | L2: KWH | P2: 45639 | Q2: 45673 | R2: 12 | S2: 2024 | T2: 1
A3: Electric | B3: RO | C3: RIVER OAKS RV RESORT | D3: TECO | E3: 212WHITESQUIRREL | F3: 04/05/2025 - 05/05/2025 | G3: 30 | H3: 2025 | I3: May | J3: 0 | K3: 0 | L3: KWH | P3: 45752 | Q3: 45782 | R3: 4 | S3: 2025 | T3: 5
A4: Electric | B4: RO | C4: RIVER OAKS RV RESORT | D4: TECO | E4: 216WHITESQUIRREL | F4: 12/27/2024 - 01/27/2025 | G4: 31 | H4: 2025 | I4: Jan | J4: 14.11 | K4: 0 | L4: KWH | O4: RESIDENTIAL SERVICE | P4: 45653 | Q4: 45684 | R4: 12 | S4: 2024 | T4: 1
A5: Electric | B5: RO | C5: RIVER OAKS RV RESORT | D5: TECO | E5: 216WHITESQUIRREL | F5: 11/23/2024 - 12/26/2024 | G5: 33 | H5: 2025 | I5: Jan | J5: 24.76 | K5: 0 | L5: KWH | O5: RESIDENTIAL SERVICE | P5: 45619 | Q5: 45652 | R5: 11 | S5: 2024 | T5: 12
A6: Electric | B6: RO | C6: RIVER OAKS RV RESORT | D6: TECO | E6: 2716DANCINGMULLET | F6: 12/27/2024 - 01/27/2025 | G6: 31 | H6: 2025 | I6: Jan | J6: 14.11 | K6: 0 | L6: KWH | O6: RESIDENTIAL SERVICE | P6: 45653 | Q6: 45684 | R6: 12 | S6: 2024 | T6: 1
A7: Electric | B7: RO | C7: RIVER OAKS RV RESORT | D7: TECO | E7: 2716DANCINGMULLET | F7: 11/23/2024 - 12/26/2024 | G7: 33 | H7: 2025 | I7: Jan | J7: 24.76 | K7: 0 | L7: KWH | O7: RESIDENTIAL SERVICE | P7: 45619 | Q7: 45652 | R7: 11 | S7: 2024 | T7: 12
A8: Electric | B8: RO | C8: RIVER OAKS RV RESORT | D8: TECO | E8: 2718DANCINGMULLET | F8: 12/27/2024 - 01/27/2025 | G8: 31 | H8: 2025 | I8: Jan | J8: 19.11 | K8: 0 | L8: KWH | O8: RESIDENTIAL SERVICE | P8: 45653 | Q8: 45684 | R8: 12 | S8: 2024 | T8: 1
A9: Electric | B9: RO | C9: RIVER OAKS RV RESORT | D9: TECO | E9: 2718DANCINGMULLET | F9: 11/26/2024 - 12/26/2024 | G9: 30 | H9: 2025 | I9: Jan | J9: 22.57 | K9: 0 | L9: KWH | O9: RESIDENTIAL SERVICE | P9: 45622 | Q9: 45652 | R9: 11 | S9: 2024 | T9: 12
A10: Electric | B10: RO | C10: RIVER OAKS RV RESORT | D10: TECO | E10: 2732DANCINGMULLET | F10: 12/27/2024 - 01/27/2025 | G10: 31 | H10: 2025 | I10: Jan | J10: 14.11 | K10: 0 | L10: KWH | P10: 45653 | Q10: 45684 | R10: 12 | S10: 2024 | T10: 1
A11: Electric | B11: RO | C11: RIVER OAKS RV RESORT | D11: TECO | E11: 2732DANCINGMULLET | F11: 11/23/2024 - 12/26/2024 | G11: 33 | H11: 2025 | I11: Jan | J11: 24.76 | K11: 0 | L11: KWH | O11: RESIDENTIAL SERVICE | P11: 45619 | Q11: 45652 | R11: 11 | S11: 2024 | T11: 12
A12: Electric | B12: SOUTH | C12: SOUTHGATE MOBILE HOMES | D12: FPL | E12: 318817NATLANTIC | F12: 01/15/2025 - 02/17/2025 | G12: 33 | H12: 2025 | I12: Feb | J12: 34.9 | K12: 0 | L12: KWH | O12: RS-1 RESIDENTIAL SERVICE | P12: 45672 | Q12: 45705 | R12: 1 | S12: 2025 | T12: 2
A13: Electric | B13: SOUTH | C13: SOUTHGATE MOBILE HOMES | D13: FPL | E13: 318817NATLANTIC | F13: 01/15/2025 - 02/17/2025 | G13: 33 | H13: 2025 | I13: Feb | J13: 34.9 | K13: 0 | L13: KWH | O13: RS-1 RESIDENTIAL SERVICE | P13: 45672 | Q13: 45705 | R13: 1 | S13: 2025 | T13: 2
A14: Electric | B14: WPMH | C14: WHISPERING PINES MH | D14: FPL | E14: 354LILY | F14: 02/17/2025 - 03/19/2025 | G14: 30 | H14: 2025 | I14: Mar | J14: 0 | K14: 0 | L14: KWH | P14: 45705 | Q14: 45735 | R14: 2 | S14: 2025 | T14: 3
A15: Electric | B15: WPMH | C15: WHISPERING PINES MH | D15: FPL | E15: 359CHENEY | F15: 12/30/2024 - 01/06/2025 | G15: 7 | H15: 2025 | I15: Jan | J15: 123.6 | K15: 785 | L15: KWH | O15: RS-1 RESIDENTIAL SERVICE | P15: 45656 | Q15: 45663 | R15: 12 | S15: 2024 | T15: 1
A16: Electric | B16: WPMH | C16: WHISPERING PINES MH | D16: FPL | E16: 359CHENEY | F16: 12/30/2024 - 01/06/2025 | G16: 7 | H16: 2025 | I16: Jan | J16: 123.6 | K16: 785 | L16: KWH | O16: RS-1 RESIDENTIAL SERVICE | P16: 45656 | Q16: 45663 | R16: 12 | S16: 2024 | T16: 1
A17: Water | B17: HSRC | C17: HUNTER SPRINGS MHC | D17: CITY OF CRYSTAL RIVER | E17: 1316NE2ND | F17: 03/19/2025 - 04/21/2025 | G17: 33 | H17: 2025 | I17: Apr | J17: 10.13 | K17: 0 | L17: GAL | O17: 1PH35 | P17: 45735 | Q17: 45768 | R17: 3 | S17: 2025 | T17: 4
A18: Water | B18: HSRC | C18: HUNTER SPRINGS MHC | D18: CITY OF CRYSTAL RIVER | E18: 1316NE2ND | F18: 02/19/2025 - 03/19/2025 | G18: 28 | H18: 2025 | I18: Mar | J18: 11.14 | K18: 0 | L18: GAL | P18: 45707 | Q18: 45735 | R18: 2 | S18: 2025 | T18: 3
A19: Water | B19: HSRC | C19: HUNTER SPRINGS MHC | D19: CITY OF CRYSTAL RIVER | E19: 1316NE2ND | F19: 12/19/2024 - 01/21/2025 | G19: 33 | H19: 2025 | I19: Jan | J19: 21.27 | K19: 0 | L19: GAL | P19: 45645 | Q19: 45678 | R19: 12 | S19: 2024 | T19: 1
A20: Water | B20: WPMH | C20: WHISPERING PINES MH | D20: CITY OF TITUSVILLE | E20: 350LILY | F20: 04/08/2025 - 05/14/2025 | G20: 36 | H20: 2025 | I20: May | J20: 12.28 | K20: 0 | L20: GAL | P20: 45755 | Q20: 45791 | R20: 4 | S20: 2025 | T20: 5
A21: Water | B21: WPMH | C21: WHISPERING PINES MH | D21: CITY OF TITUSVILLE | E21: 350LILY | F21: 03/28/2025 - 04/08/2025 | G21: 11 | H21: 2025 | I21: Apr | J21: 16.2 | K21: 1000 | L21: GAL | P21: 45744 | Q21: 45755 | R21: 3 | S21: 2025 | T21: 4
A22: Water | B22: WPMH | C22: WHISPERING PINES MH | D22: CITY OF TITUSVILLE | E22: 350LILY | F22: 12/10/2024 - 01/21/2025 | G22: 42 | H22: 2025 | I22: Jan | J22: 16.52 | K22: 0 | L22: GAL | P22: 45636 | Q22: 45678 | R22: 12 | S22: 2024 | T22: 1
A23: Water | B23: WPMH | C23: WHISPERING PINES MH | D23: CITY OF TITUSVILLE | E23: 350LILY | F23: 11/06/2024 - 12/10/2024 | G23: 34 | H23: 2025 | I23: Jan | J23: 24.49 | K23: 0 | L23: GAL | P23: 45602 | Q23: 45636 | R23: 11 | S23: 2024 | T23: 12
A24: Water | B24: WPMH | C24: WHISPERING PINES MH | D24: CITY OF TITUSVILLE | E24: 359DAISY | F24: 04/08/2025 - 05/14/2025 | G24: 36 | H24: 2025 | I24: May | J24: 12.28 | K24: 0 | L24: GAL | P24: 45755 | Q24: 45791 | R24: 4 | S24: 2025 | T24: 5
A25: Water | B25: WPMH | C25: WHISPERING PINES MH | D25: CITY OF TITUSVILLE | E25: 359DAISY | F25: 03/12/2025 - 04/08/2025 | G25: 27 | H25: 2025 | I25: Apr | J25: 12.28 | K25: 0 | L25: GAL | P25: 45728 | Q25: 45755 | R25: 3 | S25: 2025 | T25: 4
A26: Water | B26: WPMH | C26: WHISPERING PINES MH | D26: CITY OF TITUSVILLE | E26: 359DAISY | F26: 02/12/2025 - 03/12/2025 | G26: 28 | H26: 2025 | I26: Apr | J26: 12.28 | K26: 0 | L26: GAL | P26: 45700 | Q26: 45728 | R26: 2 | S26: 2025 | T26: 3
A27: Water | B27: WPMH | C27: WHISPERING PINES MH | D27: CITY OF TITUSVILLE | E27: 359DAISY | F27: 01/08/2025 - 02/12/2025 | G27: 35 | H27: 2025 | I27: Feb | J27: 12.28 | K27: 0 | L27: GAL | P27: 45665 | Q27: 45700 | R27: 1 | S27: 2025 | T27: 2
A28: Water | B28: WPMH | C28: WHISPERING PINES MH | D28: CITY OF TITUSVILLE | E28: 359DAISY | F28: 12/10/2024 - 01/08/2025 | G28: 29 | H28: 2025 | I28: Jan | J28: 14.31 | K28: 0 | L28: GAL | P28: 45636 | Q28: 45665 | R28: 12 | S28: 2024 | T28: 1
A29: Water | B29: WPMH | C29: WHISPERING PINES MH | D29: CITY OF TITUSVILLE | E29: 359DAISY | F29: 11/06/2024 - 12/10/2024 | G29: 34 | H29: 2025 | I29: Jan | J29: 44.83 | K29: 0 | L29: GAL | P29: 45602 | Q29: 45636 | R29: 11 | S29: 2024 | T29: 12
... A55: Water | B55: AMER | C55: AMERICAN MHP | D55: AUBURN WATER DISTRICT | E55: 29220 | F55: 12/19/2024 - 03/21/2025 | G55: 92 | H55: 2025 | I55: Apr | J55: 13359.84 | K55: 7599411 | L55: GAL | P55: 45645 | Q55: 45737 | R55: 12 | S55: 2024 | T55: 3
A56: Water | B56: AMER | C56: AMERICAN MHP | D56: AUBURN WATER DISTRICT | E56: 29220 | F56: 09/23/2024 - 12/19/2024 | G56: 87 | H56: 2025 | I56: Jan | J56: 11716.96 | K56: 788392 | L56: GAL | O56: None | P56: 45558 | Q56: 45645 | R56: 9 | S56: 2024 | T56: 12
A57: Water | B57: BELL | C57: BELLE HAVEN | D57: PINELLAS COUNTY UTILITIES | E57: 100200051882 | F57: 03/06/2025 - 05/05/2025 | G57: 60 | H57: 2025 | I57: May | J57: 2101.89 | K57: 494000 | L57: GAL | P57: 45722 | Q57: 45782 | R57: 3 | S57: 2025 | T57: 5
A58: Water | B58: BELL | C58: BELLE HAVEN | D58: PINELLAS COUNTY UTILITIES | E58: 100200051882 | F58: 02/03/2025 - 03/03/2025 | G58: 28 | H58: 2025 | I58: Mar | J58: 4002.5 | K58: 0 | L58: GAL | P58: 45691 | Q58: 45719 | R58: 2 | S58: 2025 | T58: 3
A59: Water | B59: BELL | C59: BELLE HAVEN | D59: PINELLAS COUNTY UTILITIES | E59: 100200051882 | F59: 12/03/2024 - 01/02/2025 | G59: 30 | H59: 2025 | I59: Jan | J59: 4085.31 | K59: 0 | L59: GAL | P59: 45629 | Q59: 45659 | R59: 12 | S59: 2024 | T59: 1
A60: Water | B60: CARL | C60: CARLEY S MOBILE HOME PARK | D60: CITY OF HIALEAH | E60: 235032000 | F60: 02/06/2025 - 04/08/2025 | G60: 61 | H60: 2025 | I60: Apr | J60: 6324.51 | K60: 0 | L60: GAL | P60: 45694 | Q60: 45755 | R60: 2 | S60: 2025 | T60: 4
A61: Water | B61: CARL | C61: CARLEY S MOBILE HOME PARK | D61: CITY OF HIALEAH | E61: 235032000 | F61: 11/25/2024 - 01/28/2025 | G61: 64 | H61: 2025 | I61: Feb | J61: 3490.09 | K61: 518000 | L61: GAL | P61: 45621 | Q61: 45685 | R61: 11 | S61: 2024 | T61: 1
A62: Water | B62: CARL | C62: CARLEY S MOBILE HOME PARK | D62: CITY OF HIALEAH | E62: 235033000 | F62: 02/06/2025 - 04/08/2025 | G62: 61 | H62: 2025 | I62: Apr | J62: 6059.29 | K62: 0 | L62: GAL | P62: 45694 | Q62: 45755 | R62: 2 | S62: 2025 | T62: 4
A63: Water | B63: CARL | C63: CARLEY S MOBILE HOME PARK | D63: CITY OF HIALEAH | E63: 235033000 | F63: 11/25/2024 - 01/28/2025 | G63: 64 | H63: 2025 | I63: Feb | J63: 5902.69 | K63: 960200 | L63: GAL | P63: 45621 | Q63: 45685 | R63: 11 | S63: 2024 | T63: 1
A64: Water | B64: CENTHARB | C64: CENTRAL MOBILE HOME PARK | D64: CITY OF COCOA | E64: 48972111978 | F64: 04/16/2025 - 05/21/2025 | G64: 35 | H64: 2025 | I64: May | J64: 0 | K64: 0 | L64: GAL | P64: 45763 | Q64: 45798 | R64: 4 | S64: 2025 | T64: 5
A65: Water | B65: CENTHARB | C65: CENTRAL MOBILE HOME PARK | D65: CITY OF COCOA | E65: 48972111978 | F65: 03/18/2025 - 04/16/2025 | G65: 29 | H65: 2025 | I65: Apr | J65: 3932.48 | K65: 288000 | L65: GAL | P65: 45734 | Q65: 45763 | R65: 3 | S65: 2025 | T65: 4
A66: Water | B66: CENTHARB | C66: CENTRAL MOBILE HOME PARK | D66: CITY OF COCOA | E66: 48972111978 | F66: 02/14/2025 - 03/18/2025 | G66: 32 | H66: 2025 | I66: Mar | J66: 4458.54 | K66: 321000 | L66: GAL | P66: 45702 | Q66: 45734 | R66: 2 | S66: 2025 | T66: 3
A67: Water | B67: CENTHARB | C67: CENTRAL MOBILE HOME PARK | D67: CITY OF COCOA | E67: 48972111978 | F67: 01/17/2025 - 02/14/2025 | G67: 28 | H67: 2025 | I67: Feb | J67: 3089.09 | K67: 268000 | L67: GAL | P67: 45674 | Q67: 45702 | R67: 1 | S67: 2025 | T67: 2
A68: Water | B68: CENTHARB | C68: CENTRAL MOBILE HOME PARK | D68: CITY OF COCOA | E68: 48972111978 | F68: 12/13/2024 - 01/17/2025 | G68: 35 | H68: 2025 | I68: Jan | J68: 4498.42 | K68: 320000 | L68: GAL | P68: 45639 | Q68: 45674 | R68: 12 | S68: 2024 | T68: 1
A69: Water | B69: CONG | C69: CONGRESS MOBILE HOME PARK | D69: PALM BEACH COUNTY WTR UTIL DPT | E69: 1000901242 | F69: 04/24/2025 - 05/23/2025 | G69: 29 | H69: 2025 | I69: Jun | J69: 1041.53 | K69: 227000 | L69: GAL | O69: R | P69: 45771 | Q69: 45800 | R69: 4 | S69: 2025 | T69: 5
A70: Water | B70: CONG | C70: CONGRESS MOBILE HOME PARK | D70: PALM BEACH COUNTY WTR UTIL DPT | E70: 1000901242 | F70: 03/26/2025 - 04/24/2025 | G70: 29 | H70: 2025 | I70: May | J70: 952.49 | K70: 206000 | L70: GAL | O70: None | P70: 45742 | Q70: 45771 | R70: 3 | S70: 2025 | T70: 4
A71: Water | B71: CONG | C71: CONGRESS MOBILE HOME PARK | D71: PALM BEACH COUNTY WTR UTIL DPT | E71: 1000901242 | F71: 03/04/2025 - 03/26/2025 | G71: 22 | H71: 2025 | I71: Apr | J71: 1522.86 | K71: 330000 | L71: GAL | O71: None | P71: 45720 | Q71: 45742 | R71: 3 | S71: 2025 | T71: 3
A72: Water | B72: CONG | C72: CONGRESS MOBILE HOME PARK | D72: PALM BEACH COUNTY WTR UTIL DPT | E72: 1000901242 | F72: 01/31/2025 - 03/04/2025 | G72: 32 | H72: 2025 | I72: Mar | J72: 2282.65 | K72: 462000 | L72: GAL | O72: None | P72: 45688 | Q72: 45720 | R72: 1 | S72: 2025 | T72: 3
A73: Water | B73: CONG | C73: CONGRESS MOBILE HOME PARK | D73: PALM BEACH COUNTY WTR UTIL DPT | E73: 1000901242 | F73: 01/02/2025 - 01/31/2025 | G73: 29 | H73: 2025 | I73: Feb | J73: 1405.06 | K73: 0 | L73: GAL | O73: None | P73: 45659 | Q73: 45688 | R73: 1 | S73: 2025 | T73: 1
A74: Water | B74: GKRV | C74: GEIGER KEY RESORT | D74: FLORIDA KEYS AQUEDUCT AUTH | E74: 625824016545 | F74: 04/11/2025 - 04/11/2025 | G74: 0 | H74: 2025 | I74: Apr | J74: 2915.77 | K74: 0 | L74: GAL | O74: None | P74: 45758 | Q74: 45758 | R74: 4 | S74: 2025 | T74: 4
A75: Water | B75: GKRV | C75: GEIGER KEY RESORT | D75: FLORIDA KEYS AQUEDUCT AUTH | E75: 625824016545 | F75: 03/29/2025 - 04/30/2025 | G75: 32 | H75: 2025 | I75: Apr | J75: 816.59 | K75: 50874 | L75: GAL | O75: None | P75: 45745 | Q75: 45777 | R75: 3 | S75: 2025 | T75: 4
A76: Water | B76: GKRV | C76: GEIGER KEY RESORT | D76: FLORIDA KEYS AQUEDUCT AUTH | E76: 625824016545 | F76: 02/20/2025 - 03/21/2025 | G76: 29 | H76: 2025 | I76: Mar | J76: 812.11 | K76: 46733 | L76: GAL | O76: None | P76: 45708 | Q76: 45737 | R76: 2 | S76: 2025 | T76: 3
A77: Water | B77: GKRV | C77: GEIGER KEY RESORT | D77: FLORIDA KEYS AQUEDUCT AUTH | E77: 625824016545 | F77: 12/18/2024 - 01/24/2025 | G77: 37 | H77: 2025 | I77: Jan | J77: 841.02 | K77: 52141 | L77: GAL | P77: 45644 | Q77: 45681 | R77: 12 | S77: 2024 | T77: 1
A78: Water | B78: GKRV | C78: GEIGER KEY RESORT | D78: FLORIDA KEYS AQUEDUCT AUTH | E78: 625824017798 | F78: 06/06/2025 - 06/06/2025 | G78: 0 | H78: 2025 | I78: Jun | J78: 217.55 | K78: 0 | L78: GAL | O78: None | P78: 45814 | Q78: 45814 | R78: 6 | S78: 2025 | T78: 6
A79: Water | B79: GKRV | C79: GEIGER KEY RESORT | D79: FLORIDA KEYS AQUEDUCT AUTH | E79: 625824017798 | F79: 03/29/2025 - 04/30/2025 | G79: 32 | H79: 2025 | I79: Apr | J79: 61.09 | K79: 3976 | L79: GAL | O79: None | P79: 45745 | Q79: 45777 | R79: 3 | S79: 2025 | T79: 4
A80: Water | B80: GKRV | C80: GEIGER KEY RESORT | D80: FLORIDA KEYS AQUEDUCT AUTH | E80: 625824017798 | F80: 03/28/2025 - 04/11/2025 | G80: 14 | H80: 2025 | I80: Apr | J80: 246.24 | K80: 0 | L80: GAL | O80: None | P80: 45744 | Q80: 45758 | R80: 3 | S80: 2025 | T80: 4
A81: Water | B81: GKRV | C81: GEIGER KEY RESORT | D81: FLORIDA KEYS AQUEDUCT AUTH | E81: 625824017798 | F81: 02/21/2025 - 03/21/2025 | G81: 28 | H81: 2025 | I81: Mar | J81: 54.01 | K81: 2789 | L81: GAL | O81: None | P81: 45709 | Q81: 45737 | R81: 2 | S81: 2025 | T81: 3
A82: Water | B82: GKRV | C82: GEIGER KEY RESORT | D82: FLORIDA KEYS AQUEDUCT AUTH | E82: 625824017798 | F82: 12/18/2024 - 01/24/2025 | G82: 37 | H82: 2025 | I82: Jan | J82: 165.05 | K82: 2258 | L82: GAL | P82: 45644 | Q82: 45681 | R82: 12 | S82: 2024 | T82: 1
A83: Water | B83: GKRV | C83: GEIGER KEY RESORT | D83: FLORIDA KEYS AQUEDUCT AUTH | E83: 625824017798 | F83: 12/18/2024 - 01/24/2025 | G83: 37 | H83: 2025 | I83: Jan | J83: 0 | K83: 0 | L83: GAL | P83: 45644 | Q83: 45681 | R83: 12 | S83: 2024 | T83: 1
A84: Water | B84: GKRV | C84: GEIGER KEY RESORT | D84: FLORIDA KEYS AQUEDUCT AUTH | E84: 625824020815 | F84: 03/29/2025 - 04/30/2025 | G84: 32 | H84: 2025 | I84: Apr | J84: 650.47 | K84: 41504 | L84: GAL | O84: None | P84: 45745 | Q84: 45777 | R84: 3 | S84: 2025 | T84: 4
A85: Water | B85: GKRV | C85: GEIGER KEY RESORT | D85: FLORIDA KEYS AQUEDUCT AUTH | E85: 625824020815 | F85: 03/28/2025 - 04/11/2025 | G85: 14 | H85: 2025 | I85: Apr | J85: 2035.85 | K85: 0 | L85: GAL | O85: None | P85: 45744 | Q85: 45758 | R85: 3 | S85: 2025 | T85: 4
A86: Water | B86: GKRV | C86: GEIGER KEY RESORT | D86: FLORIDA KEYS AQUEDUCT AUTH | E86: 625824020815 | F86: 02/21/2025 - 03/21/2025 | G86: 28 | H86: 2025 | I86: Mar | J86: 584.53 | K86: 35231 | L86: GAL | O86: None | P86: 45709 | Q86: 45737 | R86: 2 | S86: 2025 | T86: 3
A87: Water | B87: GKRV | C87: GEIGER KEY RESORT | D87: FLORIDA KEYS AQUEDUCT AUTH | E87: 625824020815 | F87: 12/18/2024 - 01/24/2025 | G87: 37 | H87: 2025 | I87: Jan | J87: 568.66 | K87: 36848 | L87: GAL | P87: 45644 | Q87: 45681 | R87: 12 | S87: 2024 | T87: 1
A88: Water | B88: GKRV | C88: GEIGER KEY RESORT | D88: FLORIDA KEYS AQUEDUCT AUTH | E88: 625824021397 | F88: 03/29/2025 - 04/30/2025 | G88: 32 | H88: 2025 | I88: Apr | J88: 1693.09 | K88: 107566 | L88: GAL | O88: None | P88: 45745 | Q88: 45777 | R88: 3 | S88: 2025 | T88: 4
A89: Water | B89: GKRV | C89: GEIGER KEY RESORT | D89: FLORIDA KEYS AQUEDUCT AUTH | E89: 625824021397 | F89: 03/28/2025 - 04/11/2025 | G89: 14 | H89: 2025 | I89: Apr | J89: 6370.46 | K89: 0 | L89: GAL | O89: None | P89: 45744 | Q89: 45758 | R89: 3 | S89: 2025 | T89: 4
A90: Water | B90: GKRV | C90: GEIGER KEY RESORT | D90: FLORIDA KEYS AQUEDUCT AUTH | E90: 625824021397 | F90: 02/21/2025 - 03/21/2025 | G90: 28 | H90: 2025 | I90: Mar | J90: 1641.01 | K90: 95775 | L90: GAL | O90: None | P90: 45709 | Q90: 45737 | R90: 2 | S90: 2025 | T90: 3
A91: Water | B91: GKRV | C91: GEIGER KEY RESORT | D91: FLORIDA KEYS AQUEDUCT AUTH | E91: 625824021397 | F91: 12/18/2024 - 01/24/2025 | G91: 37 | H91: 2025 | I91: Jan | J91: 1790.26 | K91: 113096 | L91: GAL | P91: 45644 | Q91: 45681 | R91: 12 | S91: 2024 | T91: 1
A92: Water | B92: HARB | C92: HARBOUR MOBILE HOME PARK | D92: CITY OF COCOA | E92: 48971911848 | F92: 04/16/2025 - 05/16/2025 | G92: 30 | H92: 2025 | I92: May | J92: 2215.63 | K92: 159000 | L92: GAL | P92: 45763 | Q92: 45793 | R92: 4 | S92: 2025 | T92: 5
A93: Water | B93: HARB | C93: HARBOUR MOBILE HOME PARK | D93: CITY OF COCOA | E93: 48971911848 | F93: 03/18/2025 - 04/16/2025 | G93: 29 | H93: 2025 | I93: Apr | J93: 2305.99 | K93: 161000 | L93: GAL | P93: 45734 | Q93: 45763 | R93: 3 | S93: 2025 | T93: 4
A94: Water | B94: HARB | C94: HARBOUR MOBILE HOME PARK | D94: CITY OF COCOA | E94: 48971911848 | F94: 02/14/2025 - 03/18/2025 | G94: 32 | H94: 2025 | I94: Mar | J94: 2654.04 | K94: 183000 | L94: GAL | P94: 45702 | Q94: 45734 | R94: 2 | S94: 2025 | T94: 3
A95: Water | B95: HARB | C95: HARBOUR MOBILE HOME PARK | D95: CITY OF COCOA | E95: 48971911848 | F95: 01/17/2025 - 02/14/2025 | G95: 28 | H95: 2025 | I95: Feb | J95: 2291.31 | K95: 157000 | L95: GAL | P95: 45674 | Q95: 45702 | R95: 1 | S95: 2025 | T95: 2
A96: Water | B96: HARB | C96: HARBOUR MOBILE HOME PARK | D96: CITY OF COCOA | E96: 48971911848 | F96: 12/13/2024 - 01/17/2025 | G96: 35 | H96: 2025 | I96: Jan | J96: 2928.78 | K96: 188000 | L96: GAL | P96: 45639 | Q96: 45674 | R96: 12 | S96: 2024 | T96: 1
A97: Water | B97: HSRC | C97: HUNTER SPRINGS MHC | D97: CITY OF CRYSTAL RIVER | E97: 1010027600 | F97: 03/31/2025 - 04/30/2025 | G97: 30 | H97: 2025 | I97: Apr | J97: 0 | K97: 0 | L97: GAL | P97: 45747 | Q97: 45777 | R97: 3 | S97: 2025 | T97: 4
A98: Water | B98: HSRC | C98: HUNTER SPRINGS MHC | D98: CITY OF CRYSTAL RIVER | E98: 1010027600 | F98: 03/01/2025 - 03/31/2025 | G98: 30 | H98: 2025 | I98: Mar | J98: 0 | K98: 0 | L98: GAL | P98: 45717 | Q98: 45747 | R98: 3 | S98: 2025 | T98: 3
A99: Water | B99: HSRC | C99: HUNTER SPRINGS MHC | D99: CITY OF CRYSTAL RIVER | E99: 1010028605 | F99: 05/01/2025 - 05/31/2025 | G99: 30 | H99: 2025 | I99: May | J99: 14.88 | K99: 0 | L99: GAL | P99: 45778 | Q99: 45808 | R99: 5 | S99: 2025 | T99: 5
A100: Water | B100: HSRC | C100: HUNTER SPRINGS MHC | D100: CITY OF CRYSTAL RIVER | E100: 1010028605 | F100: 03/19/2025 - 04/21/2025 | G100: 33 | H100: 2025 | I100: Apr | J100: 10.13 | K100: 0 | L100: GAL | P100: 45735 | Q100: 45768 | R100: 3 | S100: 2025 | T100: 4
A101: Water | B101: HSRC | C101: HUNTER SPRINGS MHC | D101: CITY OF CRYSTAL RIVER | E101: 1010028605 | F101: 02/19/2025 - 03/19/2025 | G101: 28 | H101: 2025 | I101: Mar | J101: 11.14 | K101: 0 | L101: GAL | P101: 45707 | Q101: 45735 | R101: 2 | S101: 2025 | T101: 3
A102: Water | B102: HSRC | C102: HUNTER SPRINGS MHC | D102: CITY OF CRYSTAL RIVER | E102: 1010028605 | F102: 12/19/2024 - 01/21/2025 | G102: 33 | H102: 2025 | I102: Jan | J102: 11.14 | K102: 0 | L102: GAL | P102: 45645 | Q102: 45678 | R102: 12 | S102: 2024 | T102: 1
... A109: Water | B109: JBJ | C109: J BAR J ESTATES | D109: MIAMI DADE WATER SEWER DEPT | E109: 9770982677 | F109: 11/13/2024 - 01/13/2025 | G109: 61 | H109: 2025 | I109: Jan | J109: 7941.64 | K109: 0 | L109: GAL | P109: 45609 | Q109: 45670 | R109: 11 | S109: 2024 | T109: 1
A110: Water | B110: LLMHC | C110: LAMBERTON LAKE MHC | D110: CITY OF GRAND RAPIDS | E110: WS2159433 | F110: 04/21/2025 - 05/19/2025 | G110: 28 | H110: 2025 | I110: May | J110: 508.66 | K110: 133892 | L110: GAL | O110: None | P110: 45768 | Q110: 45796 | R110: 4 | S110: 2025 | T110: 5
A111: Water | B111: LLMHC | C111: LAMBERTON LAKE MHC | D111: CITY OF GRAND RAPIDS | E111: WS2159433 | F111: 03/20/2025 - 04/21/2025 | G111: 32 | H111: 2025 | I111: Apr | J111: 667.78 | K111: 181764 | L111: GAL | O111: None | P111: 45736 | Q111: 45768 | R111: 3 | S111: 2025 | T111: 4
A112: Water | B112: LLMHC | C112: LAMBERTON LAKE MHC | D112: CITY OF GRAND RAPIDS | E112: WS2159433 | F112: 01/21/2025 - 02/20/2025 | G112: 30 | H112: 2025 | I112: Feb | J112: 2156.47 | K112: 679184 | L112: GAL | O112: None | P112: 45678 | Q112: 45708 | R112: 1 | S112: 2025 | T112: 2
A113: Water | B113: LLMHC | C113: LAMBERTON LAKE MHC | D113: CITY OF GRAND RAPIDS | E113: WS2159433 | F113: 12/20/2024 - 01/21/2025 | G113: 32 | H113: 2025 | I113: Jan | J113: 880.84 | K113: 220660 | L113: GAL | P113: 45646 | Q113: 45678 | R113: 12 | S113: 2024 | T113: 1
A114: Water | B114: LS | C114: LAKE SAUNDERS | D114: CITY OF MOUNT DORA | E114: 000000069798 | F114: 04/21/2025 - 05/19/2025 | G114: 28 | H114: 2025 | I114: May | J114: 937.21 | K114: 98000 | L114: GAL | O114: None | P114: 45768 | Q114: 45796 | R114: 4 | S114: 2025 | T114: 5
A115: Water | B115: LS | C115: LAKE SAUNDERS | D115: CITY OF MOUNT DORA | E115: 000000069798 | F115: 03/24/2025 - 04/21/2025 | G115: 28 | H115: 2025 | I115: Apr | J115: 919.4 | K115: 100100 | L115: GAL | P115: 45740 | Q115: 45768 | R115: 3 | S115: 2025 | T115: 4
A116: Water | B116: LS | C116: LAKE SAUNDERS | D116: CITY OF MOUNT DORA | E116: 000000069798 | F116: 02/18/2025 - 03/24/2025 | G116: 34 | H116: 2025 | I116: Mar | J116: 999.25 | K116: 115900 | L116: GAL | O116: None | P116: 45706 | Q116: 45740 | R116: 2 | S116: 2025 | T116: 3
A117: Water | B117: LS | C117: LAKE SAUNDERS | D117: CITY OF MOUNT DORA | E117: 000000069798 | F117: 01/21/2025 - 02/18/2025 | G117: 28 | H117: 2025 | I117: Feb | J117: 919.4 | K117: 100100 | L117: GAL | O117: None | P117: 45678 | Q117: 45706 | R117: 1 | S117: 2025 | T117: 2
A118: Water | B118: LS | C118: LAKE SAUNDERS | D118: CITY OF MOUNT DORA | E118: 000000069798 | F118: 12/19/2024 - 01/21/2025 | G118: 33 | H118: 2025 | I118: Jan | J118: 1112.13 | K118: 115900 | L118: GAL | O118: None | P118: 45645 | Q118: 45678 | R118: 12 | S118: 2024 | T118: 1
A119: Water | B119: LUCK | C119: LUCKY CLOVER MOBILE HOME & RV | D119: CITY OF MELBOURNE UTILITIES | E119: 107182412433 | F119: 03/26/2025 - 04/23/2025 | G119: 28 | H119: 2025 | I119: May | J119: 1625.57 | K119: 224000 | L119: GAL | P119: 45742 | Q119: 45770 | R119: 3 | S119: 2025 | T119: 4
A120: Water | B120: LUCK | C120: LUCKY CLOVER MOBILE HOME & RV | D120: CITY OF MELBOURNE UTILITIES | E120: 107182412433 | F120: 02/26/2025 - 03/26/2025 | G120: 28 | H120: 2025 | I120: Apr | J120: 1645.84 | K120: 227600 | L120: GAL | P120: 45714 | Q120: 45742 | R120: 2 | S120: 2025 | T120: 3
A121: Water | B121: LUCK | C121: LUCKY CLOVER MOBILE HOME & RV | D121: CITY OF MELBOURNE UTILITIES | E121: 107182412433 | F121: 01/29/2025 - 02/26/2025 | G121: 28 | H121: 2025 | I121: Mar | J121: 1627.26 | K121: 224300 | L121: GAL | P121: 45686 | Q121: 45714 | R121: 1 | S121: 2025 | T121: 2
A122: Water | B122: LUCK | C122: LUCKY CLOVER MOBILE HOME & RV | D122: CITY OF MELBOURNE UTILITIES | E122: 107182412433 | F122: 12/30/2024 - 01/29/2025 | G122: 30 | H122: 2025 | I122: Feb | J122: 1607.55 | K122: 220800 | L122: GAL | P122: 45656 | Q122: 45686 | R122: 12 | S122: 2024 | T122: 1
A123: Water | B123: LUCK | C123: LUCKY CLOVER MOBILE HOME & RV | D123: CITY OF MELBOURNE UTILITIES | E123: 107182412433 | F123: 11/27/2024 - 12/30/2024 | G123: 33 | H123: 2025 | I123: Jan | J123: 1813.18 | K123: 252400 | L123: GAL | P123: 45623 | Q123: 45656 | R123: 11 | S123: 2024 | T123: 12
A124: Water | B124: LW | C124: LAKE WALES MHC | D124: CITY OF LAKE WALES | E124: 51079 | F124: 05/15/2025 - 06/17/2025 | G124: 33 | H124: 2025 | I124: Jun | J124: 590.99 | K124: 73000 | L124: GAL | O124: WA | P124: 45792 | Q124: 45825 | R124: 5 | S124: 2025 | T124: 6
A125: Water | B125: LW | C125: LAKE WALES MHC | D125: CITY OF LAKE WALES | E125: 51079 | F125: 04/16/2025 - 05/15/2025 | G125: 29 | H125: 2025 | I125: May | J125: 564.11 | K125: 64000 | L125: GAL | P125: 45763 | Q125: 45792 | R125: 4 | S125: 2025 | T125: 5
A126: Water | B126: LW | C126: LAKE WALES MHC | D126: CITY OF LAKE WALES | E126: 51079 | F126: 03/20/2025 - 04/16/2025 | G126: 27 | H126: 2025 | I126: Apr | J126: 465.87 | K126: 66000 | L126: GAL | P126: 45736 | Q126: 45763 | R126: 3 | S126: 2025 | T126: 4
A127: Water | B127: LW | C127: LAKE WALES MHC | D127: CITY OF LAKE WALES | E127: 51079 | F127: 02/17/2025 - 03/20/2025 | G127: 31 | H127: 2025 | I127: Mar | J127: 632.22 | K127: 88000 | L127: GAL | O127: None | P127: 45705 | Q127: 45736 | R127: 2 | S127: 2025 | T127: 3
A128: Water | B128: LW | C128: LAKE WALES MHC | D128: CITY OF LAKE WALES | E128: 51079 | F128: 01/16/2025 - 02/17/2025 | G128: 32 | H128: 2025 | I128: Feb | J128: 609.89 | K128: 72000 | L128: GAL | O128: None | P128: 45673 | Q128: 45705 | R128: 1 | S128: 2025 | T128: 2
A129: Water | B129: MAY | C129: MAYFLOWER HILLS | D129: TOWN OF PLYMOUTH | E129: 8410 | F129: 01/09/2025 - 04/02/2025 | G129: 83 | H129: 2025 | I129: May | J129: 4024.72 | K129: 87700 | L129: GAL | O129: None | P129: 45666 | Q129: 45749 | R129: 1 | S129: 2025 | T129: 4
A130: Water | B130: MAY | C130: MAYFLOWER HILLS | D130: TOWN OF PLYMOUTH | E130: 8410 | F130: 10/10/2024 - 01/09/2025 | G130: 91 | H130: 2025 | I130: Feb | J130: 4445.25 | K130: 100100 | L130: GAL | O130: None | P130: 45575 | Q130: 45666 | R130: 10 | S130: 2024 | T130: 1
A131: Water | B131: MON | C131: MONSON MHC | D131: TOWN OF MONSON | E131: 0992 | F131: 12/31/2024 - 04/01/2025 | G131: 91 | H131: 2025 | I131: Apr | J131: 13263.8 | K131: 2022000 | L131: GAL | O131: None | P131: 45657 | Q131: 45748 | R131: 12 | S131: 2024 | T131: 4
...

Sheet Site-Level RFI
I1: Asset Management | M1: Occupancy | Q1: Utility Type and Data | AD1: Green Initiatives
